setup.py
rolling_measures/__init__.py
rolling_measures.egg-info/PKG-INFO
rolling_measures.egg-info/SOURCES.txt
rolling_measures.egg-info/dependency_links.txt
rolling_measures.egg-info/top_level.txt