Metadata-Version: 1.0
Name: rolling-measures
Version: 0.0.5
Summary: Rolling measures of data like standard deviation and average
Home-page: https://github.com/SkyTruth/rolling_measures
Author: Egil Moeller
Author-email: egil@skytruth.org
License: GPL
Keywords: measures rolling
Platform: UNKNOWN
